EducRating/__init__.py
EducRating/attempt.py
EducRating/elo.py
EducRating/elo_with_uncertainty.py
EducRating/m_elo.py
EducRating/mv_glicko.py
EducRating-0.0.11.dist-info/LICENSE
EducRating-0.0.11.dist-info/METADATA
EducRating-0.0.11.dist-info/WHEEL
EducRating-0.0.11.dist-info/top_level.txt
EducRating-0.0.11.dist-info/RECORD
